atribucion/__init__.py
atribucion/heuristicos.py
atribucion/markov.py
atribucion/modeloAtribucion.py
atribucion/shapley.py
atribucion-2.3.dist-info/METADATA
atribucion-2.3.dist-info/WHEEL
atribucion-2.3.dist-info/top_level.txt
atribucion-2.3.dist-info/RECORD
