Metadata-Version: 2.1
Name: atribucion
Version: 2.3
Summary: Libreria para correr modelos de atribucion para marketing digital
Home-page: https://github.com/tomasrene/atribucion
Author: Tomas Reneboldi
Author-email: tomasrene@gmail.com
License: UNKNOWN
Platform: UNKNOWN
Classifier: Programming Language :: Python
Classifier: Programming Language :: Python :: 3
Classifier: Programming Language :: Python :: 3.6
Classifier: Programming Language :: Python :: 3.7
Classifier: Programming Language :: Python :: 3.8
Classifier: Programming Language :: Python :: 3.9
Classifier: Operating System :: OS Independent
Requires-Dist: pandas
Requires-Dist: numpy
